bldr_test/__init__.py
bldr_test/__main__.py
bldr_test/main.py
bldr_test/py.typed
bldr_test-0.4.2.dist-info/WHEEL
bldr_test-0.4.2.dist-info/entry_points.txt
bldr_test-0.4.2.dist-info/METADATA
bldr_test-0.4.2.dist-info/RECORD
