Metadata-Version: 2.1
Name: bldr-test
Version: 0.4.2
Summary: 
Author: Ethan Skowronski-Lutz
Author-email: 33399972+ethanmsl@users.noreply.github.com
Requires-Python: >=3.10,<4.0
Classifier: Programming Language :: Python :: 3
Classifier: Programming Language :: Python :: 3.10
Classifier: Programming Language :: Python :: 3.11
Requires-Dist: typer[all] (>=0.7.0,<0.8.0)
